flexexecutor-0.0.11.dist-info/METADATA
flexexecutor-0.0.11.dist-info/WHEEL
flexexecutor-0.0.11.dist-info/licenses/LICENSE
flexexecutor.py
flexexecutor-0.0.11.dist-info/RECORD
