Metadata-Version: 2.1
Name: flexexecutor
Version: 0.0.11
Summary: Executors for both async and sync functions and automatically scales the number of workers
Home-page: https://github.com/leavers/flexexecutor
Author: leavers
Author-Email: Leavers <leavers930@gmail.com>
License: MIT
Classifier: Intended Audience :: Developers
Classifier: License :: OSI Approved :: MIT License
Classifier: Operating System :: OS Independent
Classifier: Programming Language :: Python
Classifier: Programming Language :: Python :: 3
Classifier: Programming Language :: Python :: 3.8
Classifier: Programming Language :: Python :: 3.9
Classifier: Programming Language :: Python :: 3.10
Classifier: Programming Language :: Python :: 3.11
Classifier: Programming Language :: Python :: 3.12
Classifier: Topic :: Software Development
Classifier: Topic :: Software Development :: Libraries :: Python Modules
Classifier: Topic :: Utilities
Project-URL: Homepage, https://github.com/leavers/flexexecutor
Project-URL: Documentation, https://github.com/leavers/flexexecutor/blob/main/README.md
Requires-Python: >=3.8
